physDBD/__init__.py
physDBD/comparison_model.py
physDBD/data_desc.py
physDBD/diff_tvr.py
physDBD/helpers.py
physDBD/import_helper.py
physDBD/net.py
physDBD/params.py
physDBD/paramsTE.py
physDBD/paramsTE_traj.py
physDBD/params_traj.py
physDBD/rxn_model.py
physPCA/__init__.py
physPCA/data_desc.py
physPCA/diff_tvr.py
physPCA/helpers.py
physPCA/import_helper.py
physPCA/net.py
physPCA/params.py
physPCA/paramsTE.py
physPCA/paramsTE_traj.py
physPCA/params_traj.py
physDBD-0.1.1.dist-info/LICENSE
physDBD-0.1.1.dist-info/METADATA
physDBD-0.1.1.dist-info/WHEEL
physDBD-0.1.1.dist-info/top_level.txt
physDBD-0.1.1.dist-info/RECORD
