Metadata-Version: 2.1
Name: physDBD
Version: 0.1.1
Summary: Physics-based modeling of reaction networks with TensorFlow
Home-page: https://github.com/smrfeld/phys_dbd
Author: Oliver K. Ernst
Author-email: oernst@ucsd.edu
License: UNKNOWN
Platform: UNKNOWN
Requires-Python: >=3.7
License-File: LICENSE
